axisutilities/__init__.py
axisutilities/_version.py
axisutilities/axisbinding.py
axisutilities/axisbuilder.py
axisutilities/axisremapper.py
axisutilities/constants.py
axisutilities/core.py
axisutilities/timeaxisbuilders.py
tests/__init__.py
tests/test_AxisBuilder.py
tests/test_TimeAxisBuilder.py
tests/test_timeAxis.py
tests/test_timeAxisBinding.py
tests/test_timeAxisConverter.py
tests/test_timeInterval.py
AxisUtilities-19.12.6.36596.dist-info/LICENSE
AxisUtilities-19.12.6.36596.dist-info/METADATA
AxisUtilities-19.12.6.36596.dist-info/WHEEL
AxisUtilities-19.12.6.36596.dist-info/top_level.txt
AxisUtilities-19.12.6.36596.dist-info/RECORD
