Metadata-Version: 2.1
Name: AxisUtilities
Version: 19.12.6.36596
Summary: UNKNOWN
Home-page: https://github.com/coderepocenter/AxisUtilities.git
Author: Mohammad Abouali
Author-email: maboualidev@gmail.com
License: UNKNOWN
Platform: UNKNOWN
Classifier: Programming Language :: Python :: 3
Classifier: Operating System :: OS Independent
Requires-Python: >=3.7
Requires-Dist: numpy
Requires-Dist: cftime
Requires-Dist: scipy
Requires-Dist: numba
Requires-Dist: dask[complete]
